convert2json-0.0.2.dist-info/METADATA
convert2json-0.0.2.dist-info/RECORD
convert2json-0.0.2.dist-info/WHEEL
convert2json-0.0.2.dist-info/top_level.txt
src/__init__.py
